[
    {
        "Nama Produk":"Sarung Songket Modern Sarung Premium Sarung Dewasa",
        "jumlah_pesanan_unik":344,
        "jumlah_terjual":1219,
        "total_penjualan":19491.17
    },
    {
        "Nama Produk":"SMCollection - Sarung Travel Songket Kemasan Pouch",
        "jumlah_pesanan_unik":226,
        "jumlah_terjual":1095,
        "total_penjualan":15288.0
    },
    {
        "Nama Produk":"[COD] Sarung Dewasa Sarung Motif Songket Simple Premium Termurah",
        "jumlah_pesanan_unik":221,
        "jumlah_terjual":782,
        "total_penjualan":12804.578
    },
    {
        "Nama Produk":"Sarung Dewasa Motif Songket Travel Mini Pouch Exclusive",
        "jumlah_pesanan_unik":138,
        "jumlah_terjual":595,
        "total_penjualan":8492.24
    },
    {
        "Nama Produk":"Sarkoci Anak Sarung Koko Peci Anak Usia 1-14 Tahun",
        "jumlah_pesanan_unik":95,
        "jumlah_terjual":116,
        "total_penjualan":6539.6
    },
    {
        "Nama Produk":"Sarung Dewasa Motif Sabuk Gajah Asia",
        "jumlah_pesanan_unik":93,
        "jumlah_terjual":521,
        "total_penjualan":5816.7
    },
    {
        "Nama Produk":"SMCollection - Jubah Gamis Anak Premium Koko Anak Usia 2-9 tahun",
        "jumlah_pesanan_unik":68,
        "jumlah_terjual":85,
        "total_penjualan":4726.3
    },
    {
        "Nama Produk":"Sarung Anak Laki Laki Usia 4-12 Tahun Al Jabar junior",
        "jumlah_pesanan_unik":88,
        "jumlah_terjual":113,
        "total_penjualan":2878.0
    },
    {
        "Nama Produk":"Sarung Tenun Songket Kemasan Pouch Travel Waterproof",
        "jumlah_pesanan_unik":36,
        "jumlah_terjual":115,
        "total_penjualan":2330.5
    },
    {
        "Nama Produk":"Sarung Tenun Dewasa Aljabar Guci",
        "jumlah_pesanan_unik":19,
        "jumlah_terjual":46,
        "total_penjualan":1091.0
    },
    {
        "Nama Produk":"Kain Ihram Remaja SMP Bahan Lembut Berkualitas",
        "jumlah_pesanan_unik":14,
        "jumlah_terjual":19,
        "total_penjualan":942.824
    },
    {
        "Nama Produk":"Sarung Instan Anak Karaker Untuk Usia 2-7 Tahun",
        "jumlah_pesanan_unik":17,
        "jumlah_terjual":25,
        "total_penjualan":848.0
    },
    {
        "Nama Produk":"Sarung Dewasa Aljabar Motif Balimoon Kemasan Mini Pouch Exclusive",
        "jumlah_pesanan_unik":9,
        "jumlah_terjual":25,
        "total_penjualan":775.0
    },
    {
        "Nama Produk":"Sarung Instan Anak Laki Laki Ayo Solat Umur 2-7 Tahun",
        "jumlah_pesanan_unik":17,
        "jumlah_terjual":19,
        "total_penjualan":672.0
    },
    {
        "Nama Produk":"SARUNG TENUN MURAH DEWASA SARUNG DOBY KARAWANG EXPORT QUALITY",
        "jumlah_pesanan_unik":16,
        "jumlah_terjual":92,
        "total_penjualan":628.5
    },
    {
        "Nama Produk":"Kerudung Arab Motif Import | Ukuran XL",
        "jumlah_pesanan_unik":5,
        "jumlah_terjual":5,
        "total_penjualan":625.0
    },
    {
        "Nama Produk":"COD SORBAN TENUN BERKUALITAS SORBAN ARAB ARAFAT",
        "jumlah_pesanan_unik":31,
        "jumlah_terjual":46,
        "total_penjualan":499.5
    },
    {
        "Nama Produk":"COD Sorban Arab Rumbai Motif Diamond Model Segi Empat",
        "jumlah_pesanan_unik":13,
        "jumlah_terjual":110,
        "total_penjualan":421.65
    },
    {
        "Nama Produk":"Aljabar Sarung Dewasa Motif Sabuk Palembangan Bahan Teteron Cotton Ukuran 125 x 103 cm",
        "jumlah_pesanan_unik":11,
        "jumlah_terjual":490,
        "total_penjualan":418.499
    },
    {
        "Nama Produk":"Sarung anak laki laki usia 4 - 12 Tahun Berbagai Pilihan",
        "jumlah_pesanan_unik":9,
        "jumlah_terjual":10,
        "total_penjualan":280.0
    },
    {
        "Nama Produk":"Peci Rajut Anak Polos Tebal Elastis \/ Kopiah Ngaji",
        "jumlah_pesanan_unik":16,
        "jumlah_terjual":19,
        "total_penjualan":264.7
    },
    {
        "Nama Produk":"Sarkoci Anak Motif Songket Premium Sarung Koko Peci Anak Usia 1-14 Tahun",
        "jumlah_pesanan_unik":4,
        "jumlah_terjual":4,
        "total_penjualan":261.0
    },
    {
        "Nama Produk":"Sarung Dewasa Motif Sabuk Aljabar",
        "jumlah_pesanan_unik":5,
        "jumlah_terjual":72,
        "total_penjualan":203.0
    },
    {
        "Nama Produk":"PASHMINA JERSEY | JERSEY PASHMINA",
        "jumlah_pesanan_unik":2,
        "jumlah_terjual":6,
        "total_penjualan":167.5
    },
    {
        "Nama Produk":"Sarung Aljabar Balimoon",
        "jumlah_pesanan_unik":1,
        "jumlah_terjual":20,
        "total_penjualan":164.0
    },
    {
        "Nama Produk":"SMCollection - Sarung Dewasa Motif Sabuk Gajah Mina",
        "jumlah_pesanan_unik":6,
        "jumlah_terjual":105,
        "total_penjualan":158.5
    },
    {
        "Nama Produk":"COD SORBAN HAJI AL-MINA MOTIF RUMBAI OLEH OLEH HAJI",
        "jumlah_pesanan_unik":9,
        "jumlah_terjual":21,
        "total_penjualan":153.0
    },
    {
        "Nama Produk":"Sarung Anak Black Series Tenun Murah Berkualitas",
        "jumlah_pesanan_unik":6,
        "jumlah_terjual":6,
        "total_penjualan":152.0
    },
    {
        "Nama Produk":"Sarung Anak Travel Friendly Sarung Anak Motif Songket Murah Bersahabat",
        "jumlah_pesanan_unik":4,
        "jumlah_terjual":5,
        "total_penjualan":145.0
    },
    {
        "Nama Produk":"COD SORBAN ARAB RUMBAI MOTIF OLEH OLEH HAJI DAN UMROH",
        "jumlah_pesanan_unik":3,
        "jumlah_terjual":8,
        "total_penjualan":144.0
    },
    {
        "Nama Produk":"SARUNG TENUN DEWASA BLACK SERIES",
        "jumlah_pesanan_unik":3,
        "jumlah_terjual":24,
        "total_penjualan":130.39
    },
    {
        "Nama Produk":"SARUNG MOISINO MOTIF SABUK RAIBAN POLOS DEWASA TERLARIS",
        "jumlah_pesanan_unik":3,
        "jumlah_terjual":3,
        "total_penjualan":126.0
    },
    {
        "Nama Produk":"Sajadah Kepala Anak Bludru Hitam Ukuran Kecil Motif Kiswah Termurah",
        "jumlah_pesanan_unik":7,
        "jumlah_terjual":7,
        "total_penjualan":117.5
    },
    {
        "Nama Produk":"Kain Ihram Anak SD Bahan Lembut Berkualitas",
        "jumlah_pesanan_unik":2,
        "jumlah_terjual":2,
        "total_penjualan":111.0
    },
    {
        "Nama Produk":"Sarung Celana Anak Black Series",
        "jumlah_pesanan_unik":2,
        "jumlah_terjual":2,
        "total_penjualan":83.0
    },
    {
        "Nama Produk":"Ciput Rajut 2 Warna \/ Bandana Rajut \/ Inner Rajut 2 Warna",
        "jumlah_pesanan_unik":4,
        "jumlah_terjual":7,
        "total_penjualan":65.55
    },
    {
        "Nama Produk":"Mukena Travel Mini Pouch Parasut Korea 2 in 1 Free Tasbih Digital",
        "jumlah_pesanan_unik":1,
        "jumlah_terjual":1,
        "total_penjualan":60.0
    },
    {
        "Nama Produk":"Sarung Anak Polos Tumpal Salur Warna Original",
        "jumlah_pesanan_unik":2,
        "jumlah_terjual":2,
        "total_penjualan":56.0
    },
    {
        "Nama Produk":"Sarung Anak Laki Laki - Sarung Anak Motif Songket",
        "jumlah_pesanan_unik":2,
        "jumlah_terjual":2,
        "total_penjualan":56.0
    },
    {
        "Nama Produk":"Sarung anak laki laki umur 4-12 Tahun Motif Matahari",
        "jumlah_pesanan_unik":2,
        "jumlah_terjual":7,
        "total_penjualan":55.0
    },
    {
        "Nama Produk":"SMCollection - Sarung Celana Dewasa Motif Donggala Lama",
        "jumlah_pesanan_unik":1,
        "jumlah_terjual":1,
        "total_penjualan":49.5
    },
    {
        "Nama Produk":"SM Collection - Ciput Rajut \/ Bandana Rajut \/ Inner Hijab Satu Warna",
        "jumlah_pesanan_unik":3,
        "jumlah_terjual":5,
        "total_penjualan":44.1
    },
    {
        "Nama Produk":"Tas Sarung Mini Travel Anti air",
        "jumlah_pesanan_unik":4,
        "jumlah_terjual":57,
        "total_penjualan":39.0
    },
    {
        "Nama Produk":"SORBAN ARAFAT MOTIF BINTIK MURAH BERKUALITAS",
        "jumlah_pesanan_unik":2,
        "jumlah_terjual":28,
        "total_penjualan":25.5
    },
    {
        "Nama Produk":"KHUSUS YANG TIDAK MAU PENYOK SATUAN DUS SARUNGNYA PAKAI INI Packing Dus Tambahan Untuk Mengurangi Penyok di Perjalanan",
        "jumlah_pesanan_unik":5,
        "jumlah_terjual":5,
        "total_penjualan":19.0
    },
    {
        "Nama Produk":"Tasbih Digital Mini Alat Hitung Elektronik Finger Tally Counter Mini Jari Penghitung",
        "jumlah_pesanan_unik":3,
        "jumlah_terjual":5,
        "total_penjualan":16.5
    },
    {
        "Nama Produk":"Packing Dus Tambahan Untuk Mengurangi Penyok di Perjalanan",
        "jumlah_pesanan_unik":3,
        "jumlah_terjual":3,
        "total_penjualan":15.0
    },
    {
        "Nama Produk":"SORBAN HAJI PUTIH SORBAN ARAFAT MOTIF POLOS TERMURAH",
        "jumlah_pesanan_unik":1,
        "jumlah_terjual":2,
        "total_penjualan":11.0
    }
]