[
    {
        "Nama Produk":"[COD] Sarung Dewasa Sarung Motif Songket Simple Premium Termurah",
        "jumlah_pesanan_unik":605,
        "jumlah_terjual":2277,
        "total_penjualan":30649.227
    },
    {
        "Nama Produk":"Sarung Songket Modern Sarung Premium Sarung Dewasa",
        "jumlah_pesanan_unik":297,
        "jumlah_terjual":1129,
        "total_penjualan":17406.191
    },
    {
        "Nama Produk":"Sarung Dewasa Motif Songket Travel Mini Pouch Exclusive",
        "jumlah_pesanan_unik":160,
        "jumlah_terjual":765,
        "total_penjualan":11923.892
    },
    {
        "Nama Produk":"Sarkoci Anak Sarung Koko Peci Anak Usia 1-14 Tahun",
        "jumlah_pesanan_unik":166,
        "jumlah_terjual":199,
        "total_penjualan":10079.8
    },
    {
        "Nama Produk":"Sarung Dewasa Motif Sabuk Gajah Asia",
        "jumlah_pesanan_unik":192,
        "jumlah_terjual":1187,
        "total_penjualan":9491.361
    },
    {
        "Nama Produk":"SMCollection - Sarung Travel Songket Kemasan Pouch",
        "jumlah_pesanan_unik":127,
        "jumlah_terjual":649,
        "total_penjualan":8420.977
    },
    {
        "Nama Produk":"Sarung Travel Motif Songket Kemasan Pouch Waterproof - Sarung Dewasa Untuk Sholat",
        "jumlah_pesanan_unik":32,
        "jumlah_terjual":180,
        "total_penjualan":2295.0
    },
    {
        "Nama Produk":"COD SORBAN TENUN BERKUALITAS SORBAN ARAB ARAFAT",
        "jumlah_pesanan_unik":124,
        "jumlah_terjual":302,
        "total_penjualan":1799.121
    },
    {
        "Nama Produk":"SMCollection - Jubah Gamis Anak Premium Koko Anak Usia 2-9 tahun",
        "jumlah_pesanan_unik":19,
        "jumlah_terjual":23,
        "total_penjualan":1321.0
    },
    {
        "Nama Produk":"Sarung Dewasa Sarung Tenun Muslim Termurah",
        "jumlah_pesanan_unik":23,
        "jumlah_terjual":62,
        "total_penjualan":1091.0
    },
    {
        "Nama Produk":"Sarung Dewasa Motif Sabuk New Gajah Asia",
        "jumlah_pesanan_unik":18,
        "jumlah_terjual":164,
        "total_penjualan":1012.6
    },
    {
        "Nama Produk":"Sarung Tenun Dewasa Sarung Songket Premium Jabar Mosi",
        "jumlah_pesanan_unik":19,
        "jumlah_terjual":31,
        "total_penjualan":898.5
    },
    {
        "Nama Produk":"Setelan Koko Peci Celana Anak Usia 1-8 Tahun",
        "jumlah_pesanan_unik":21,
        "jumlah_terjual":24,
        "total_penjualan":780.0
    },
    {
        "Nama Produk":"Aljabar Sarung Dewasa Motif Sabuk Palembang Bahan Teteron Cotton Ukuran 125 x 103 cm",
        "jumlah_pesanan_unik":17,
        "jumlah_terjual":41,
        "total_penjualan":754.0
    },
    {
        "Nama Produk":"Sarung Anak Laki Laki Usia 4-12 Tahun Al Jabar junior",
        "jumlah_pesanan_unik":24,
        "jumlah_terjual":27,
        "total_penjualan":676.0
    },
    {
        "Nama Produk":"COD Sorban Arab Rumbai Motif Diamond Model Segi Empat",
        "jumlah_pesanan_unik":17,
        "jumlah_terjual":67,
        "total_penjualan":664.0
    },
    {
        "Nama Produk":"SMCollection - Sarung Tenun Pria Dewasa Motif Songket Kemasan Travel Pouch Lonjong",
        "jumlah_pesanan_unik":8,
        "jumlah_terjual":21,
        "total_penjualan":611.375
    },
    {
        "Nama Produk":"Sarung Tenun Dewasa Aljabar Guci",
        "jumlah_pesanan_unik":14,
        "jumlah_terjual":31,
        "total_penjualan":576.0
    },
    {
        "Nama Produk":"SARUNG TENUN MURAH DEWASA SARUNG DOBY KARAWANG EXPORT QUALITY",
        "jumlah_pesanan_unik":7,
        "jumlah_terjual":33,
        "total_penjualan":566.0
    },
    {
        "Nama Produk":"SMCollection - Sarung Dewasa Motif Sabuk Gajah Mina",
        "jumlah_pesanan_unik":5,
        "jumlah_terjual":11,
        "total_penjualan":294.5
    },
    {
        "Nama Produk":"Sarkoci Anak Motif Songket Premium Sarung Koko Peci Anak Usia 1-14 Tahun",
        "jumlah_pesanan_unik":3,
        "jumlah_terjual":4,
        "total_penjualan":226.0
    },
    {
        "Nama Produk":"Sarung Instan Anak Laki Laki Ayo Solat Umur 2-7 Tahun",
        "jumlah_pesanan_unik":5,
        "jumlah_terjual":5,
        "total_penjualan":178.0
    },
    {
        "Nama Produk":"Peci Rajut Anak Polos Tebal Elastis \/ Kopiah Ngaji",
        "jumlah_pesanan_unik":5,
        "jumlah_terjual":6,
        "total_penjualan":87.0
    },
    {
        "Nama Produk":"Sarung anak laki laki usia 4 - 12 Tahun Berbagai Pilihan",
        "jumlah_pesanan_unik":3,
        "jumlah_terjual":3,
        "total_penjualan":84.0
    },
    {
        "Nama Produk":"Ekstra Packing Dus Untuk Mengurangi Penyok di Perjalanan",
        "jumlah_pesanan_unik":17,
        "jumlah_terjual":19,
        "total_penjualan":82.0
    },
    {
        "Nama Produk":"Sarung Tenun Dewasa Aljabar BM Series",
        "jumlah_pesanan_unik":1,
        "jumlah_terjual":3,
        "total_penjualan":67.0
    },
    {
        "Nama Produk":"Sarung anak laki laki umur 4-12 Tahun Motif Matahari",
        "jumlah_pesanan_unik":2,
        "jumlah_terjual":2,
        "total_penjualan":56.0
    },
    {
        "Nama Produk":"Sarung Dewasa Motif Sabuk Aljabar",
        "jumlah_pesanan_unik":2,
        "jumlah_terjual":6,
        "total_penjualan":55.0
    },
    {
        "Nama Produk":"BERGO PLISKET \/ BERGO CERUTY PREMIUM HIJAB INSTAN",
        "jumlah_pesanan_unik":2,
        "jumlah_terjual":2,
        "total_penjualan":54.0
    },
    {
        "Nama Produk":"Kemasan Tas Sarung Mini Travel Anti air & Kemasan Dus",
        "jumlah_pesanan_unik":5,
        "jumlah_terjual":120,
        "total_penjualan":50.0
    },
    {
        "Nama Produk":"Sarung Tenun Dewasa Multazam Salaka Premium",
        "jumlah_pesanan_unik":1,
        "jumlah_terjual":1,
        "total_penjualan":34.5
    },
    {
        "Nama Produk":"SMCollection Sarung Dewasa Black & White",
        "jumlah_pesanan_unik":1,
        "jumlah_terjual":14,
        "total_penjualan":31.0
    },
    {
        "Nama Produk":"Sarung Tenun Aljabar Grey Seris Sarung songket",
        "jumlah_pesanan_unik":1,
        "jumlah_terjual":1,
        "total_penjualan":30.0
    },
    {
        "Nama Produk":"COD SORBAN ARAB RUMBAI MOTIF OLEH OLEH HAJI DAN UMROH",
        "jumlah_pesanan_unik":1,
        "jumlah_terjual":1,
        "total_penjualan":25.5
    },
    {
        "Nama Produk":"Tasbih Digital Mini Alat Hitung Elektronik Finger Tally Counter Mini Jari Penghitung",
        "jumlah_pesanan_unik":2,
        "jumlah_terjual":3,
        "total_penjualan":16.5
    },
    {
        "Nama Produk":"Arafat Sorban Dewasa Motif Songket Bahan Soft Poly Premium",
        "jumlah_pesanan_unik":1,
        "jumlah_terjual":1,
        "total_penjualan":15.0
    },
    {
        "Nama Produk":"SORBAN ARAFAT MOTIF BINTIK MURAH BERKUALITAS",
        "jumlah_pesanan_unik":1,
        "jumlah_terjual":1,
        "total_penjualan":13.5
    },
    {
        "Nama Produk":"SORBAN HAJI PUTIH SORBAN ARAFAT MOTIF POLOS TERMURAH",
        "jumlah_pesanan_unik":1,
        "jumlah_terjual":1,
        "total_penjualan":11.0
    }
]